{
  "attack_type": "password_spraying",
  "target_usernames": [
    "weak_user_01",
    "weak_user_02",
    "weak_user_03",
    "weak_user_04",
    "weak_user_05",
    "weak_user_06",
    "weak_user_07",
    "weak_user_08",
    "weak_user_09",
    "weak_user_10"
  ],
  "password_category": "weak",
  "hash_mode": "SHA256",
  "protection_flags": {
    "rate_limit": true,
    "lockout": true,
    "captcha": true,
    "pepper": true,
    "totp": true
  },
  "success": false,
  "cracked_users": [],
  "total_attempts": 1,
  "time_to_crack": null,
  "total_time_seconds": 0.12335419654846191,
  "avg_latency_ms": 123.35411335601978,
  "attempts_per_second": 8.106736762758874,
  "group_seed": 1170596,
  "timestamp": 1767799000,
  "attempts": [
    {
      "attempt": 1,
      "timestamp": 1767799000,
      "group_seed": 1170596,
      "username": "weak_user_01",
      "password": "password_1",
      "password_category": "unknown",
      "hash_mode": "SHA256",
      "rate_limit": true,
      "lockout": true,
      "captcha": true,
      "pepper": true,
      "totp": true,
      "status_code": 403,
      "success": false,
      "latency_ms": 123.35411335601978,
      "error": "CAPTCHA required"
    }
  ]
}